xyston/__init__.py
xyston/fstpack.cpython-310-x86_64-linux-gnu.so
xyston/signal.py
xyston/nn/__init__.py
xyston/nn/functional.py
xyston/nn/modules/__init__.py
xyston/nn/modules/activation.py
xyston/nn/modules/conv.py
xyston/nn/modules/pooling.py
xyston-0.0.2.dist-info/LICENSE
xyston-0.0.2.dist-info/METADATA
xyston-0.0.2.dist-info/WHEEL
xyston-0.0.2.dist-info/top_level.txt
xyston-0.0.2.dist-info/RECORD
